pytest_docker_postgresql.py
pytest_docker_postgresql/docker/.env
pytest_docker_postgresql/docker/docker-compose.yml
pytest_docker_postgresql-0.1.0.dist-info/LICENSE
pytest_docker_postgresql-0.1.0.dist-info/METADATA
pytest_docker_postgresql-0.1.0.dist-info/WHEEL
pytest_docker_postgresql-0.1.0.dist-info/entry_points.txt
pytest_docker_postgresql-0.1.0.dist-info/top_level.txt
pytest_docker_postgresql-0.1.0.dist-info/RECORD
