Metadata-Version: 2.1
Name: pytest-docker-postgresql
Version: 0.1.0
Summary: A simple plugin to use with pytest
Home-page: https://github.com/loum/pytest-docker-postgresql
Author: Lou Markovski
Author-email: lou.markovski@gmail.com
Maintainer: Lou Markovski
Maintainer-email: lou.markovski@gmail.com
License: MIT
Platform: UNKNOWN
Classifier: Development Status :: 4 - Beta
Classifier: Framework :: Pytest
Classifier: Intended Audience :: Developers
Classifier: Topic :: Software Development :: Testing
Classifier: Programming Language :: Python
Classifier: Programming Language :: Python :: 3
Classifier: Programming Language :: Python :: 3.6
Classifier: Programming Language :: Python :: 3.7
Classifier: Programming Language :: Python :: Implementation :: CPython
Classifier: Programming Language :: Python :: Implementation :: PyPy
Classifier: Operating System :: OS Independent
Classifier: License :: OSI Approved :: MIT License
Requires-Python: >=3.6
Requires-Dist: backoff (>=1.8.0)
Requires-Dist: docker-compose (<=1.24.0)
Requires-Dist: lovely-pytest-docker (<=0.0.5)
Requires-Dist: pg8000 (>=1.13.2)
Requires-Dist: pytest (>=3.5.0)
Requires-Dist: requests (<2.21)
Requires-Dist: urllib3 (<1.25,>=1.21.1)
